colivara_py/__init__.py
colivara_py/api_client.py
colivara_py/api_response.py
colivara_py/client.py
colivara_py/configuration.py
colivara_py/exceptions.py
colivara_py/rest.py
colivara_py/api/__init__.py
colivara_py/api/collections_api.py
colivara_py/api/documents_api.py
colivara_py/api/embeddings_api.py
colivara_py/api/filter_api.py
colivara_py/api/health_api.py
colivara_py/api/helpers_api.py
colivara_py/api/search_api.py
colivara_py/api/webhook_api.py
colivara_py/models/__init__.py
colivara_py/models/collection_in.py
colivara_py/models/collection_out.py
colivara_py/models/document_in.py
colivara_py/models/document_in_patch.py
colivara_py/models/document_out.py
colivara_py/models/embeddings_in.py
colivara_py/models/embeddings_out.py
colivara_py/models/file_out.py
colivara_py/models/generic_error.py
colivara_py/models/generic_message.py
colivara_py/models/key.py
colivara_py/models/lookup_enum.py
colivara_py/models/on_enum.py
colivara_py/models/page_out.py
colivara_py/models/page_out_query.py
colivara_py/models/patch_collection_in.py
colivara_py/models/query_filter.py
colivara_py/models/query_in.py
colivara_py/models/query_out.py
colivara_py/models/response.py
colivara_py/models/search_image_in.py
colivara_py/models/search_image_out.py
colivara_py/models/task_enum.py
colivara_py/models/value.py
colivara_py/models/webhook_in.py
colivara_py/models/webhook_out.py
colivara_py-1.6.2.dist-info/LICENSE
colivara_py-1.6.2.dist-info/METADATA
colivara_py-1.6.2.dist-info/WHEEL
colivara_py-1.6.2.dist-info/top_level.txt
colivara_py-1.6.2.dist-info/RECORD
