Metadata-Version: 2.2
Name: colivara-py
Version: 1.6.2
Summary: The official Python SDK for the ColiVara API
Author: tjmlabs
Project-URL: Homepage, https://github.com/tjmlabs/colivara-py
Project-URL: Changelog, https://github.com/tjmlabs/colivara-py/releases
Project-URL: Issues, https://github.com/tjmlabs/colivara-py/issues
Project-URL: CI, https://github.com/tjmlabs/colivara-py/actions
Classifier: License :: OSI Approved :: Apache Software License
Requires-Python: >=3.9
License-File: LICENSE
Requires-Dist: urllib3<3.0.0,>=1.25.3
Requires-Dist: python-dateutil>=2.8.2
Requires-Dist: pydantic>=2
Requires-Dist: typing-extensions>=4.7.1
Requires-Dist: svix==1.40.0
